gameai_frame
