Metadata-Version: 1.2
Name: gameai-frame
Version: 0.1.5
Summary: :)
Home-page: https://github.com/Iyrian/GameAI-Frame-
Author: Ehekatl
Author-email: 2072498313@qq.com
Maintainer: Ehekatl
Maintainer-email: 2072498313@qq.com
License: MIT License
Platform: all
Classifier: Programming Language :: Python :: 3.6
Classifier: Topic :: Software Development :: Libraries
